htmlrunner_simple-0.2.0.dist-info/licenses/LICENSE
htmlsimple/__init__.py
htmlsimple/main.py
htmlrunner_simple-0.2.0.dist-info/METADATA
htmlrunner_simple-0.2.0.dist-info/WHEEL
htmlrunner_simple-0.2.0.dist-info/top_level.txt
htmlrunner_simple-0.2.0.dist-info/RECORD
